pico_sqlalchemy/__init__.py
pico_sqlalchemy/_version.py
pico_sqlalchemy/base.py
pico_sqlalchemy/config.py
pico_sqlalchemy/decorators.py
pico_sqlalchemy/factory.py
pico_sqlalchemy/interceptor.py
pico_sqlalchemy/session.py
pico_sqlalchemy-0.1.0.dist-info/licenses/LICENSE
pico_sqlalchemy-0.1.0.dist-info/METADATA
pico_sqlalchemy-0.1.0.dist-info/WHEEL
pico_sqlalchemy-0.1.0.dist-info/top_level.txt
pico_sqlalchemy-0.1.0.dist-info/RECORD
