Metadata-Version: 2.4
Name: pico-sqlalchemy
Version: 0.1.0
Summary: Pico-ioc integration for SQLAlchemy. Adds Spring-style transactional support, configuration, and helpers.
Author-email: David Perez Cabrera <dperezcabrera@gmail.com>
License: MIT License
Project-URL: Homepage, https://github.com/dperezcabrera/pico-sqlalchemy
Project-URL: Repository, https://github.com/dperezcabrera/pico-sqlalchemy
Project-URL: Issue Tracker, https://github.com/dperezcabrera/pico-sqlalchemy/issues
Keywords: ioc,di,dependency injection,sqlalchemy,transaction,orm,inversion of control,asyncio
Classifier: Development Status :: 4 - Beta
Classifier: Topic :: Software Development :: Libraries :: Python Modules
Classifier: Topic :: Database
Classifier: Programming Language :: Python :: 3
Classifier: Programming Language :: Python :: 3 :: Only
Classifier: Programming Language :: Python :: 3.10
Classifier: Programming Language :: Python :: 3.11
Classifier: Programming Language :: Python :: 3.12
Classifier: Programming Language :: Python :: 3.13
Classifier: Programming Language :: Python :: 3.14
Classifier: License :: OSI Approved :: MIT License
Classifier: Operating System :: OS Independent
Requires-Python: >=3.10
License-File: LICENSE
Requires-Dist: pico-ioc>=2.0
Requires-Dist: sqlalchemy>=2.0
Provides-Extra: async
Requires-Dist: asyncpg>=0.29.0; extra == "async"
Provides-Extra: test
Requires-Dist: pytest>=8; extra == "test"
Requires-Dist: pytest-asyncio>=0.23.5; extra == "test"
Requires-Dist: pytest-cov>=5; extra == "test"
Dynamic: license-file
